LICENSE.txt
MANIFEST.in
README.md
README.rst
setup.cfg
setup.py
direct_sdk_python3.egg-info/PKG-INFO
direct_sdk_python3.egg-info/SOURCES.txt
direct_sdk_python3.egg-info/dependency_links.txt
direct_sdk_python3.egg-info/requires.txt
direct_sdk_python3.egg-info/top_level.txt
ingenico/direct/sdk/api_exception.py
ingenico/direct/sdk/api_resource.py
ingenico/direct/sdk/authenticator.py
ingenico/direct/sdk/authorization_exception.py
ingenico/direct/sdk/call_context.py
ingenico/direct/sdk/client.py
ingenico/direct/sdk/communication_exception.py
ingenico/direct/sdk/communicator.py
ingenico/direct/sdk/communicator_configuration.py
ingenico/direct/sdk/connection.py
ingenico/direct/sdk/data_object.py
ingenico/direct/sdk/declined_payment_exception.py
ingenico/direct/sdk/declined_payout_exception.py
ingenico/direct/sdk/declined_refund_exception.py
ingenico/direct/sdk/declined_transaction_exception.py
ingenico/direct/sdk/direct_exception.py
ingenico/direct/sdk/endpoint_configuration.py
ingenico/direct/sdk/factory.py
ingenico/direct/sdk/i_client.py
ingenico/direct/sdk/idempotence_exception.py
ingenico/direct/sdk/marshaller.py
ingenico/direct/sdk/marshaller_syntax_exception.py
ingenico/direct/sdk/meta_data_provider.py
ingenico/direct/sdk/not_found_exception.py
ingenico/direct/sdk/param_request.py
ingenico/direct/sdk/pooled_connection.py
ingenico/direct/sdk/proxy_configuration.py
ingenico/direct/sdk/reference_exception.py
ingenico/direct/sdk/request_header.py
ingenico/direct/sdk/request_param.py
ingenico/direct/sdk/response_exception.py
ingenico/direct/sdk/response_header.py
ingenico/direct/sdk/validation_exception.py
ingenico/direct/sdk/defaultimpl/authorization_type.py
ingenico/direct/sdk/defaultimpl/default_authenticator.py
ingenico/direct/sdk/defaultimpl/default_connection.py
ingenico/direct/sdk/defaultimpl/default_marshaller.py
ingenico/direct/sdk/domain/account_on_file.py
ingenico/direct/sdk/domain/account_on_file_attribute.py
ingenico/direct/sdk/domain/account_on_file_display_hints.py
ingenico/direct/sdk/domain/additional_order_input.py
ingenico/direct/sdk/domain/address.py
ingenico/direct/sdk/domain/address_personal.py
ingenico/direct/sdk/domain/airline_data.py
