Metadata-Version: 1.1
Name: direct-sdk-python3
Version: 1.8.0
Summary: SDK to communicate with the Ingenico ePayments platform using the Ingenico Direct Server API
Home-page: https://github.com/Ingenico/direct-sdk-python3
Author: Ingenico dev team
Author-email: 60233882+ingenico-dev-team@users.noreply.github.com
License: MIT
Keywords: Ingenico ePayments Direct SDK
Platform: python 3.5
Classifier: Development Status :: 5 - Production/Stable
Classifier: Operating System :: POSIX :: Linux
Classifier: Operating System :: Microsoft :: Windows
Classifier: Intended Audience :: Developers
Classifier: Programming Language :: Python :: 3 :: Only
Classifier: Programming Language :: Python :: 3.5
Classifier: Topic :: Office/Business :: Financial
Classifier: License :: OSI Approved :: MIT License
